RoyceAPocPyPi/RoyceAPocPyPi.py
RoyceAPocPyPi/__init__.py
RoyceAPocPyPi/test.py
RoyceAPocPyPi-0.0.10.dist-info/LICENSE.txt
RoyceAPocPyPi-0.0.10.dist-info/METADATA
RoyceAPocPyPi-0.0.10.dist-info/WHEEL
RoyceAPocPyPi-0.0.10.dist-info/top_level.txt
RoyceAPocPyPi-0.0.10.dist-info/RECORD
