Metadata-Version: 2.1
Name: RoyceAPocPyPi
Version: 0.0.10
Summary: HVA
Home-page: UNKNOWN
Author: Daniel van den Bosch
Author-email: daniel-vd-bosch@hotmail.com
License: MIT
Keywords: test
Platform: UNKNOWN
